CHANGES.rst
CONTRIBUTORS.rst
DEVELOP.rst
LICENSE
LICENSE.GPL
LICENSE.rst
MANIFEST.in
README.rst
constraints.txt
constraints_plone52.txt
constraints_plone60.txt
requirements.txt
requirements_plone52.txt
requirements_plone60.txt
setup.cfg
setup.py
docs/conf.py
docs/index.rst
src/collective/__init__.py
src/collective.volto.footer.egg-info/PKG-INFO
src/collective.volto.footer.egg-info/SOURCES.txt
src/collective.volto.footer.egg-info/dependency_links.txt
src/collective.volto.footer.egg-info/entry_points.txt
src/collective.volto.footer.egg-info/namespace_packages.txt
src/collective.volto.footer.egg-info/not-zip-safe
src/collective.volto.footer.egg-info/requires.txt
src/collective.volto.footer.egg-info/top_level.txt
src/collective/volto/__init__.py
src/collective/volto/footer/__init__.py
src/collective/volto/footer/configure.zcml
src/collective/volto/footer/interfaces.py
src/collective/volto/footer/permissions.zcml
src/collective/volto/footer/setuphandlers.py
src/collective/volto/footer/testing.py
src/collective/volto/footer/behaviors/__init__.py
src/collective/volto/footer/behaviors/configure.zcml
src/collective/volto/footer/behaviors/footer.py
src/collective/volto/footer/browser/__init__.py
src/collective/volto/footer/browser/configure.zcml
src/collective/volto/footer/locales/__init__.py
src/collective/volto/footer/locales/collective.volto.footer.pot
src/collective/volto/footer/locales/update.py
src/collective/volto/footer/locales/en/LC_MESSAGES/collective.volto.footer.po
src/collective/volto/footer/profiles/default/browserlayer.xml
src/collective/volto/footer/profiles/default/catalog.xml
src/collective/volto/footer/profiles/default/metadata.xml
src/collective/volto/footer/profiles/default/rolemap.xml
src/collective/volto/footer/profiles/default/types.xml
src/collective/volto/footer/profiles/default/registry/main.xml
src/collective/volto/footer/profiles/default/types/Plone_Site.xml
src/collective/volto/footer/profiles/uninstall/browserlayer.xml
src/collective/volto/footer/tests/__init__.py
src/collective/volto/footer/tests/test_behavior_editable_footer.py
src/collective/volto/footer/tests/test_setup.py