Metadata-Version: 2.1
Name: collective.volto.footer
Version: 1.1
Summary: An add-on for Plone
Home-page: https://github.com/collective/collective.volto.footer
Author: Alin Voinea
Author-email: contact@avoinea.com
License: GPL version 2
Project-URL: PyPI, https://pypi.org/project/collective.volto.footer/
Project-URL: Source, https://github.com/collective/collective.volto.footer
Project-URL: Tracker, https://github.com/collective/collective.volto.footer/issues
Keywords: Python Plone CMS
Platform: UNKNOWN
Classifier: Environment :: Web Environment
Classifier: Framework :: Plone
Classifier: Framework :: Plone :: Addon
Classifier: Framework :: Plone :: 6.0
Classifier: Programming Language :: Python
Classifier: Programming Language :: Python :: 3.11
Classifier: Operating System :: OS Independent
Classifier: License :: OSI Approved :: GNU General Public License v2 (GPLv2)
Requires-Python: >=3.7
Provides-Extra: test
License-File: LICENSE
License-File: LICENSE.GPL
License-File: LICENSE.rst
